budiajimatrix/__init__.py
budiajimatrix/operations.py
budiajimatrix-1.0.0.dist-info/licenses/LICENSE
budiajimatrix-1.0.0.dist-info/METADATA
budiajimatrix-1.0.0.dist-info/WHEEL
budiajimatrix-1.0.0.dist-info/top_level.txt
budiajimatrix-1.0.0.dist-info/RECORD
