Metadata-Version: 2.4
Name: budiajimatrix
Version: 1.0.0
Summary: Library pengolahan matrix lengkap untuk Python - cocok untuk time series, GSTAR, VARIMA, dan analisis statistik
Home-page: https://github.com/ferdianwijayabangkit/budiajimatrix
Author: Ferdian Bangkit Wijaya
Author-email: ferdian.bangkit@untirta.ac.id
Project-URL: Bug Reports, https://github.com/ferdianwijayabangkit/budiajimatrix/issues
Project-URL: Source, https://github.com/ferdianwijayabangkit/budiajimatrix
Keywords: matrix,linear algebra,statistics,time series,GSTAR,VARIMA,numpy,scipy
Classifier: Development Status :: 5 - Production/Stable
Classifier: Intended Audience :: Science/Research
Classifier: Intended Audience :: Developers
Classifier: Topic :: Scientific/Engineering :: Mathematics
Classifier: Topic :: Software Development :: Libraries :: Python Modules
Classifier: License :: OSI Approved :: MIT License
Classifier: Programming Language :: Python :: 3
Classifier: Programming Language :: Python :: 3.7
Classifier: Programming Language :: Python :: 3.8
Classifier: Programming Language :: Python :: 3.9
Classifier: Programming Language :: Python :: 3.10
Classifier: Programming Language :: Python :: 3.11
Classifier: Programming Language :: Python :: 3.12
Classifier: Operating System :: OS Independent
Requires-Python: >=3.7
License-File: LICENSE
Requires-Dist: numpy>=1.18.0
Requires-Dist: scipy>=1.4.0
Provides-Extra: dev
Requires-Dist: pytest>=6.0; extra == "dev"
Requires-Dist: pytest-cov>=2.0; extra == "dev"
Requires-Dist: black>=20.8b1; extra == "dev"
Requires-Dist: flake8>=3.8.0; extra == "dev"
Dynamic: author
Dynamic: author-email
Dynamic: classifier
Dynamic: description
Dynamic: description-content-type
Dynamic: home-page
Dynamic: keywords
Dynamic: license-file
Dynamic: project-url
Dynamic: provides-extra
Dynamic: requires-dist
Dynamic: requires-python
Dynamic: summary
